heatmapcluster.py
heatmapcluster-0.1.2.dist-info/DESCRIPTION.rst
heatmapcluster-0.1.2.dist-info/METADATA
heatmapcluster-0.1.2.dist-info/RECORD
heatmapcluster-0.1.2.dist-info/WHEEL
heatmapcluster-0.1.2.dist-info/metadata.json
heatmapcluster-0.1.2.dist-info/top_level.txt
