Metadata-Version: 2.0
Name: heatmapcluster
Version: 0.1.2
Summary: Heatmap cluster dendrogram plotter.
Home-page: UNKNOWN
Author: Warren Weckesser
Author-email: UNKNOWN
License: BSD
Keywords: heatmap cluster scipy plot
Platform: UNKNOWN
Classifier: License :: OSI Approved :: BSD License
Classifier: Intended Audience :: Developers
Classifier: Operating System :: OS Independent
Classifier: Programming Language :: Python :: 2.7
Classifier: Programming Language :: Python :: 3
Requires-Dist: matplotlib
Requires-Dist: numpy (>=1.6.0)
Requires-Dist: scipy
